{
  "project_info": {
    "project_number": "1016861858540",
    "project_id": "gramin-seva-45aaf",
    "storage_bucket": "gramin-seva-45aaf.firebasestorage.app"
  },
  "client": [
    {
      "client_info": {
        "mobilesdk_app_id": "1:1016861858540:android:8d52906f2501b25da3a3c9",
        "android_client_info": {
          "package_name": "com.graminseva.graminseva"
        }
      },
      "oauth_client": [],
      "api_key": [
        {
          "current_key": "AIzaSyDlZ5ULdQWArlSCUXVnpoOrPO-h0c2b5ew"
        }
      ],
      "services": {
        "appinvite_service": {
          "other_platform_oauth_client": []
        }
      }
    }
  ],
  "configuration_version": "1"
}